graphdiff/__init__.py
graphdiff/__main__.py
graphdiff/graphdiff.py
tests/__init__.py
tests/test_sanity.py
graphdiff-0.0.1.dist-info/LICENSE
graphdiff-0.0.1.dist-info/METADATA
graphdiff-0.0.1.dist-info/WHEEL
graphdiff-0.0.1.dist-info/top_level.txt
graphdiff-0.0.1.dist-info/RECORD
