Metadata-Version: 2.1
Name: graphdiff
Version: 0.0.1
Summary: UNKNOWN
Home-page: https://github.com/yeger00/
Author: Avi Yeger
Author-email: yeger00@gmail.com
License: UNKNOWN
Platform: UNKNOWN
Requires-Dist: pydot
